[
  {
    "POSTAL_CODE": "X1A 3K4",
    "LATITUDE": "62.443829",
    "LONGITUDE": "-114.419531"
  },
  {
    "POSTAL_CODE": "X1A 2C5",
    "LATITUDE": "62.449714",
    "LONGITUDE": "-114.387193"
  },
  {
    "POSTAL_CODE": "X1A 2L3",
    "LATITUDE": "62.444816",
    "LONGITUDE": "-114.395475"
  },
  {
    "POSTAL_CODE": "X1A 3L4",
    "LATITUDE": "62.445471",
    "LONGITUDE": "-114.421025"
  },
  {
    "POSTAL_CODE": "X1A 2L7",
    "LATITUDE": "62.466912",
    "LONGITUDE": "-114.348625"
  },
  {
    "POSTAL_CODE": "X1A 3B8",
    "LATITUDE": "62.43857",
    "LONGITUDE": "-114.416775"
  },
  {
    "POSTAL_CODE": "X1A 2P1",
    "LATITUDE": "62.451557",
    "LONGITUDE": "-114.3747"
  },
  {
    "POSTAL_CODE": "X1A 1K9",
    "LATITUDE": "62.45277",
    "LONGITUDE": "-114.355929"
  },
  {
    "POSTAL_CODE": "X1A 3Y7",
    "LATITUDE": "62.44335",
    "LONGITUDE": "-114.413274"
  },
  {
    "POSTAL_CODE": "X0E 1Z0",
    "LATITUDE": "60.412993",
    "LONGITUDE": "-121.13487"
  },
  {
    "POSTAL_CODE": "X1A 1X3",
    "LATITUDE": "62.44949",
    "LONGITUDE": "-114.373712"
  },
  {
    "POSTAL_CODE": "X1A 3L7",
    "LATITUDE": "62.445429",
    "LONGITUDE": "-114.421733"
  },
  {
    "POSTAL_CODE": "X1A 3E6",
    "LATITUDE": "62.438771",
    "LONGITUDE": "-114.418154"
  },
  {
    "POSTAL_CODE": "X1A 3M6",
    "LATITUDE": "62.442846",
    "LONGITUDE": "-114.42541"
  },
  {
    "POSTAL_CODE": "X1A 3L1",
    "LATITUDE": "62.4439151",
    "LONGITUDE": "-114.4289834"
  },
  {
    "POSTAL_CODE": "X1A 3G9",
    "LATITUDE": "62.442076",
    "LONGITUDE": "-114.429561"
  },
  {
    "POSTAL_CODE": "X1A 2R8",
    "LATITUDE": "62.45595",
    "LONGITUDE": "-114.373043"
  },
  {
    "POSTAL_CODE": "X1A 2A5",
    "LATITUDE": "62.4431127",
    "LONGITUDE": "-114.4002455"
  },
  {
    "POSTAL_CODE": "X1A 2E2",
    "LATITUDE": "62.46147",
    "LONGITUDE": "-114.35196"
  },
  {
    "POSTAL_CODE": "X1A 0G1",
    "LATITUDE": "62.434000",
    "LONGITUDE": "-114.421147"
  },
  {
    "POSTAL_CODE": "X1A 1Z7",
    "LATITUDE": "62.4617305",
    "LONGITUDE": "-114.3514607"
  },
  {
    "POSTAL_CODE": "X1A 1T3",
    "LATITUDE": "62.453914",
    "LONGITUDE": "-114.375979"
  },
  {
    "POSTAL_CODE": "X1A 1A6",
    "LATITUDE": "62.458602",
    "LONGITUDE": "-114.365616"
  },
  {
    "POSTAL_CODE": "X1A 3T8",
    "LATITUDE": "62.451909",
    "LONGITUDE": "-114.423849"
  },
  {
    "POSTAL_CODE": "X1A 0E1",
    "LATITUDE": "62.450827",
    "LONGITUDE": "-114.383734"
  },
  {
    "POSTAL_CODE": "X1A 1Y5",
    "LATITUDE": "62.448608",
    "LONGITUDE": "-114.381708"
  },
  {
    "POSTAL_CODE": "X1A 3Z5",
    "LATITUDE": "62.451388",
    "LONGITUDE": "-114.370699"
  },
  {
    "POSTAL_CODE": "X1A 3T9",
    "LATITUDE": "62.451957",
    "LONGITUDE": "-114.423727"
  },
  {
    "POSTAL_CODE": "X1A 3H6",
    "LATITUDE": "62.441782",
    "LONGITUDE": "-114.42876"
  },
  {
    "POSTAL_CODE": "X1A 0A1",
    "LATITUDE": "62.440341",
    "LONGITUDE": "-114.41747"
  },
  {
    "POSTAL_CODE": "X1A 3L9",
    "LATITUDE": "62.444215",
    "LONGITUDE": "-114.428714"
  },
  {
    "POSTAL_CODE": "X1A 1Z8",
    "LATITUDE": "62.45996",
    "LONGITUDE": "-114.354893"
  },
  {
    "POSTAL_CODE": "X1A 1X8",
    "LATITUDE": "62.451706",
    "LONGITUDE": "-114.381939"
  },
  {
    "POSTAL_CODE": "X1A 2N8",
    "LATITUDE": "62.455811",
    "LONGITUDE": "-114.375116"
  },
  {
    "POSTAL_CODE": "X0E 0A0",
    "LATITUDE": "68.221032",
    "LONGITUDE": "-135.00437"
  },
  {
    "POSTAL_CODE": "X1A 2Y1",
    "LATITUDE": "62.441903",
    "LONGITUDE": "-114.403297"
  },
  {
    "POSTAL_CODE": "X1A 1M1",
    "LATITUDE": "62.4550815",
    "LONGITUDE": "-114.366786"
  },
  {
    "POSTAL_CODE": "X1A 1S5",
    "LATITUDE": "62.4533489",
    "LONGITUDE": "-114.3727048"
  },
  {
    "POSTAL_CODE": "X1A 1E5",
    "LATITUDE": "62.452325",
    "LONGITUDE": "-114.375383"
  },
  {
    "POSTAL_CODE": "X1A 1N2",
    "LATITUDE": "62.453631",
    "LONGITUDE": "-114.364759"
  },
  {
    "POSTAL_CODE": "X1A 3J6",
    "LATITUDE": "62.436569",
    "LONGITUDE": "-114.422657"
  },
  {
    "POSTAL_CODE": "X1A 2H7",
    "LATITUDE": "62.468313",
    "LONGITUDE": "-114.347705"
  },
  {
    "POSTAL_CODE": "X1A 3J3",
    "LATITUDE": "62.442036",
    "LONGITUDE": "-114.411615"
  },
  {
    "POSTAL_CODE": "X1A 3V3",
    "LATITUDE": "62.452692",
    "LONGITUDE": "-114.41128"
  },
  {
    "POSTAL_CODE": "X1A 3J8",
    "LATITUDE": "62.440909",
    "LONGITUDE": "-114.420355"
  },
  {
    "POSTAL_CODE": "X1A 1N1",
    "LATITUDE": "62.45363",
    "LONGITUDE": "-114.364759"
  },
  {
    "POSTAL_CODE": "X1A 1Y6",
    "LATITUDE": "62.447941",
    "LONGITUDE": "-114.379809"
  },
  {
    "POSTAL_CODE": "X1A 1A5",
    "LATITUDE": "62.458552",
    "LONGITUDE": "-114.365747"
  },
  {
    "POSTAL_CODE": "X1A 2B5",
    "LATITUDE": "62.44764",
    "LONGITUDE": "-114.384842"
  },
  {
    "POSTAL_CODE": "X1A 3W9",
    "LATITUDE": "62.4403991",
    "LONGITUDE": "-114.4070247"
  },
  {
    "POSTAL_CODE": "X1A 2P4",
    "LATITUDE": "62.45194",
    "LONGITUDE": "-114.368314"
  },
  {
    "POSTAL_CODE": "X1A 2T7",
    "LATITUDE": "62.449286",
    "LONGITUDE": "-114.35867"
  },
  {
    "POSTAL_CODE": "X1A 1E8",
    "LATITUDE": "62.450885",
    "LONGITUDE": "-114.378296"
  },
  {
    "POSTAL_CODE": "X1A 1E6",
    "LATITUDE": "62.450885",
    "LONGITUDE": "-114.378296"
  },
  {
    "POSTAL_CODE": "X1A 3A4",
    "LATITUDE": "62.440784",
    "LONGITUDE": "-114.422604"
  },
  {
    "POSTAL_CODE": "X1A 1B7",
    "LATITUDE": "62.456545",
    "LONGITUDE": "-114.366348"
  },
  {
    "POSTAL_CODE": "X1A 1L5",
    "LATITUDE": "62.4543067",
    "LONGITUDE": "-114.3624836"
  },
  {
    "POSTAL_CODE": "X0E 1A0",
    "LATITUDE": "62.404293",
    "LONGITUDE": "-110.741679"
  },
  {
    "POSTAL_CODE": "X1A 0C1",
    "LATITUDE": "62.450827",
    "LONGITUDE": "-114.383734"
  },
  {
    "POSTAL_CODE": "X1A 3Y3",
    "LATITUDE": "62.4575575",
    "LONGITUDE": "-114.3756968"
  },
  {
    "POSTAL_CODE": "X0E 0P0",
    "LATITUDE": "60.000149",
    "LONGITUDE": "-111.879562"
  },
  {
    "POSTAL_CODE": "X1A 2M4",
    "LATITUDE": "62.451874",
    "LONGITUDE": "-114.370629"
  },
  {
    "POSTAL_CODE": "X1A 2P2",
    "LATITUDE": "62.451879",
    "LONGITUDE": "-114.370629"
  },
  {
    "POSTAL_CODE": "X1A 2R6",
    "LATITUDE": "62.4517389",
    "LONGITUDE": "-114.3761776"
  },
  {
    "POSTAL_CODE": "X1A 1S9",
    "LATITUDE": "62.4502869",
    "LONGITUDE": "-114.365765"
  },
  {
    "POSTAL_CODE": "X1A 3T7",
    "LATITUDE": "62.450702",
    "LONGITUDE": "-114.424703"
  },
  {
    "POSTAL_CODE": "X1A 2W1",
    "LATITUDE": "62.444482",
    "LONGITUDE": "-114.370759"
  },
  {
    "POSTAL_CODE": "X0E 1G4",
    "LATITUDE": "60.800835",
    "LONGITUDE": "-115.698383"
  },
  {
    "POSTAL_CODE": "X1A 3T4",
    "LATITUDE": "62.46036",
    "LONGITUDE": "-114.413406"
  },
  {
    "POSTAL_CODE": "X1A 1L8",
    "LATITUDE": "62.456838",
    "LONGITUDE": "-114.370576"
  },
  {
    "POSTAL_CODE": "X0E 1N0",
    "LATITUDE": "69.333539",
    "LONGITUDE": "-123.996779"
  },
  {
    "POSTAL_CODE": "X1A 2P8",
    "LATITUDE": "62.413911",
    "LONGITUDE": "-114.126739"
  },
  {
    "POSTAL_CODE": "X1A 1L3",
    "LATITUDE": "62.455145",
    "LONGITUDE": "-114.364793"
  },
  {
    "POSTAL_CODE": "X1A 1J4",
    "LATITUDE": "62.46147",
    "LONGITUDE": "-114.35196"
  },
  {
    "POSTAL_CODE": "X1A 3T1",
    "LATITUDE": "62.453388",
    "LONGITUDE": "-114.3753"
  },
  {
    "POSTAL_CODE": "X1A 2A9",
    "LATITUDE": "62.446306",
    "LONGITUDE": "-114.3894"
  },
  {
    "POSTAL_CODE": "X0E 0R1",
    "LATITUDE": "60.556992",
    "LONGITUDE": "-116.139932"
  },
  {
    "POSTAL_CODE": "X1A 0C6",
    "LATITUDE": "62.450827",
    "LONGITUDE": "-114.383734"
  },
  {
    "POSTAL_CODE": "X1A 2Y2",
    "LATITUDE": "62.441311",
    "LONGITUDE": "-114.4040225"
  },
  {
    "POSTAL_CODE": "X1A 0B6",
    "LATITUDE": "62.453543",
    "LONGITUDE": "-114.3659869"
  },
  {
    "POSTAL_CODE": "X1A 3R4",
    "LATITUDE": "62.453208",
    "LONGITUDE": "-114.417325"
  },
  {
    "POSTAL_CODE": "X1A 3Y2",
    "LATITUDE": "62.43469",
    "LONGITUDE": "-114.413937"
  },
  {
    "POSTAL_CODE": "X1A 2J6",
    "LATITUDE": "62.46433",
    "LONGITUDE": "-114.34965"
  },
  {
    "POSTAL_CODE": "X1A 2H3",
    "LATITUDE": "62.4531013",
    "LONGITUDE": "-114.3831203"
  },
  {
    "POSTAL_CODE": "X1A 1Y3",
    "LATITUDE": "62.447737",
    "LONGITUDE": "-114.372042"
  },
  {
    "POSTAL_CODE": "X1A 3G4",
    "LATITUDE": "62.443781",
    "LONGITUDE": "-114.412453"
  },
  {
    "POSTAL_CODE": "X1A 2W3",
    "LATITUDE": "62.444977",
    "LONGITUDE": "-114.371815"
  },
  {
    "POSTAL_CODE": "X1A 1G1",
    "LATITUDE": "62.448741",
    "LONGITUDE": "-114.381959"
  },
  {
    "POSTAL_CODE": "X1A 3Y1",
    "LATITUDE": "62.441272",
    "LONGITUDE": "-114.417602"
  },
  {
    "POSTAL_CODE": "X1A 0E8",
    "LATITUDE": "62.454471",
    "LONGITUDE": "-114.375124"
  },
  {
    "POSTAL_CODE": "X1A 2T9",
    "LATITUDE": "62.470141",
    "LONGITUDE": "-114.343051"
  },
  {
    "POSTAL_CODE": "X1A 2J4",
    "LATITUDE": "62.444675",
    "LONGITUDE": "-114.385841"
  },
  {
    "POSTAL_CODE": "X1A 0G5",
    "LATITUDE": "62.431511",
    "LONGITUDE": "-114.410629"
  },
  {
    "POSTAL_CODE": "X1A 2M8",
    "LATITUDE": "62.451877",
    "LONGITUDE": "-114.370629"
  },
  {
    "POSTAL_CODE": "X1A 0A2",
    "LATITUDE": "62.4498231",
    "LONGITUDE": "-114.4537949"
  },
  {
    "POSTAL_CODE": "X0E 0B0",
    "LATITUDE": "67.440227",
    "LONGITUDE": "-133.746807"
  },
  {
    "POSTAL_CODE": "X1A 1K3",
    "LATITUDE": "62.454202",
    "LONGITUDE": "-114.359239"
  },
  {
    "POSTAL_CODE": "X1A 1A7",
    "LATITUDE": "62.45721",
    "LONGITUDE": "-114.370386"
  },
  {
    "POSTAL_CODE": "X1A 2A6",
    "LATITUDE": "62.443697",
    "LONGITUDE": "-114.396451"
  },
  {
    "POSTAL_CODE": "X0E 0H0",
    "LATITUDE": "66.25609",
    "LONGITUDE": "-128.636169"
  },
  {
    "POSTAL_CODE": "X1A 3B4",
    "LATITUDE": "62.443055",
    "LONGITUDE": "-114.408032"
  },
  {
    "POSTAL_CODE": "X1A 0A3",
    "LATITUDE": "62.4494655",
    "LONGITUDE": "-114.3715245"
  },
  {
    "POSTAL_CODE": "X1A 1T1",
    "LATITUDE": "62.450656",
    "LONGITUDE": "-114.366688"
  },
  {
    "POSTAL_CODE": "X1A 2Y3",
    "LATITUDE": "62.441752",
    "LONGITUDE": "-114.4056875"
  },
  {
    "POSTAL_CODE": "X1A 1H4",
    "LATITUDE": "62.450193",
    "LONGITUDE": "-114.359636"
  },
  {
    "POSTAL_CODE": "X1A 3C7",
    "LATITUDE": "62.438503",
    "LONGITUDE": "-114.411566"
  },
  {
    "POSTAL_CODE": "X1A 1L6",
    "LATITUDE": "62.452199",
    "LONGITUDE": "-114.356591"
  },
  {
    "POSTAL_CODE": "X1A 1V3",
    "LATITUDE": "62.453392",
    "LONGITUDE": "-114.377458"
  },
  {
    "POSTAL_CODE": "X1A 3A9",
    "LATITUDE": "62.438764",
    "LONGITUDE": "-114.413917"
  },
  {
    "POSTAL_CODE": "X1A 3C3",
    "LATITUDE": "62.420247",
    "LONGITUDE": "-114.415012"
  },
  {
    "POSTAL_CODE": "X1A 3T2",
    "LATITUDE": "62.506841",
    "LONGITUDE": "-114.38889"
  },
  {
    "POSTAL_CODE": "X0E 1G3",
    "LATITUDE": "60.8050315",
    "LONGITUDE": "-115.74206"
  },
  {
    "POSTAL_CODE": "X1A 2Z3",
    "LATITUDE": "62.439758",
    "LONGITUDE": "-114.408929"
  },
  {
    "POSTAL_CODE": "X1A 2M7",
    "LATITUDE": "62.451876",
    "LONGITUDE": "-114.370629"
  },
  {
    "POSTAL_CODE": "X1A 2V6",
    "LATITUDE": "62.445644",
    "LONGITUDE": "-114.37125"
  },
  {
    "POSTAL_CODE": "X0E 1L0",
    "LATITUDE": "67.008292",
    "LONGITUDE": "-126.014477"
  },
  {
    "POSTAL_CODE": "X1A 2W2",
    "LATITUDE": "62.4456802",
    "LONGITUDE": "-114.3714454"
  },
  {
    "POSTAL_CODE": "X1A 1Z2",
    "LATITUDE": "62.472933",
    "LONGITUDE": "-114.344093"
  },
  {
    "POSTAL_CODE": "X1A 2G5",
    "LATITUDE": "62.467929",
    "LONGITUDE": "-114.346756"
  },
  {
    "POSTAL_CODE": "X1A 0E9",
    "LATITUDE": "62.429204",
    "LONGITUDE": "-114.429094"
  },
  {
    "POSTAL_CODE": "X1A 2K7",
    "LATITUDE": "62.442651",
    "LONGITUDE": "-114.398356"
  },
  {
    "POSTAL_CODE": "X1A 3Z4",
    "LATITUDE": "62.4529599",
    "LONGITUDE": "-114.3729901"
  },
  {
    "POSTAL_CODE": "X1A 2B3",
    "LATITUDE": "62.444661",
    "LONGITUDE": "-114.374591"
  },
  {
    "POSTAL_CODE": "X1A 2Z4",
    "LATITUDE": "62.43769",
    "LONGITUDE": "-114.408527"
  },
  {
    "POSTAL_CODE": "X1A 3R5",
    "LATITUDE": "62.4418848",
    "LONGITUDE": "-114.4143868"
  },
  {
    "POSTAL_CODE": "X1A 1N9",
    "LATITUDE": "62.450424",
    "LONGITUDE": "-114.356815"
  },
  {
    "POSTAL_CODE": "X1A 3C9",
    "LATITUDE": "62.459928",
    "LONGITUDE": "-114.3589935"
  },
  {
    "POSTAL_CODE": "X1A 0G9",
    "LATITUDE": "62.4539717",
    "LONGITUDE": "-114.3717887"
  },
  {
    "POSTAL_CODE": "X0E 0R9",
    "LATITUDE": "60.850555",
    "LONGITUDE": "-115.736569"
  },
  {
    "POSTAL_CODE": "X1A 1M5",
    "LATITUDE": "62.451122",
    "LONGITUDE": "-114.355697"
  },
  {
    "POSTAL_CODE": "X1A 0E3",
    "LATITUDE": "62.449145",
    "LONGITUDE": "-114.370605"
  },
  {
    "POSTAL_CODE": "X0E 1G5",
    "LATITUDE": "60.81174",
    "LONGITUDE": "-115.779344"
  },
  {
    "POSTAL_CODE": "X1A 2G6",
    "LATITUDE": "62.467947",
    "LONGITUDE": "-114.346827"
  },
  {
    "POSTAL_CODE": "X1A 2V3",
    "LATITUDE": "62.444216",
    "LONGITUDE": "-114.370744"
  },
  {
    "POSTAL_CODE": "X1A 2S7",
    "LATITUDE": "62.450237",
    "LONGITUDE": "-114.383657"
  },
  {
    "POSTAL_CODE": "X1A 2L9",
    "LATITUDE": "62.455638",
    "LONGITUDE": "-114.366749"
  },
  {
    "POSTAL_CODE": "X1A 3M2",
    "LATITUDE": "62.444217",
    "LONGITUDE": "-114.425154"
  },
  {
    "POSTAL_CODE": "X1A 1E2",
    "LATITUDE": "62.452766",
    "LONGITUDE": "-114.37448"
  },
  {
    "POSTAL_CODE": "X1A 3V6",
    "LATITUDE": "62.453109",
    "LONGITUDE": "-114.422977"
  },
  {
    "POSTAL_CODE": "X1A 3N7",
    "LATITUDE": "62.439722",
    "LONGITUDE": "-114.422972"
  },
  {
    "POSTAL_CODE": "X1A 1R6",
    "LATITUDE": "62.454847",
    "LONGITUDE": "-114.373519"
  },
  {
    "POSTAL_CODE": "X1A 2C2",
    "LATITUDE": "62.451865",
    "LONGITUDE": "-114.384003"
  },
  {
    "POSTAL_CODE": "X1A 2P6",
    "LATITUDE": "62.451558",
    "LONGITUDE": "-114.3747"
  },
  {
    "POSTAL_CODE": "X1A 3N5",
    "LATITUDE": "62.440034",
    "LONGITUDE": "-114.424178"
  },
  {
    "POSTAL_CODE": "X1A 2X6",
    "LATITUDE": "62.445898",
    "LONGITUDE": "-114.400387"
  },
  {
    "POSTAL_CODE": "X1A 1N7",
    "LATITUDE": "62.450424",
    "LONGITUDE": "-114.356815"
  },
  {
    "POSTAL_CODE": "X1A 2K1",
    "LATITUDE": "62.458798",
    "LONGITUDE": "-114.355652"
  },
  {
    "POSTAL_CODE": "X1A 1E1",
    "LATITUDE": "62.452602",
    "LONGITUDE": "-114.374535"
  },
  {
    "POSTAL_CODE": "X1A 3H8",
    "LATITUDE": "62.434728",
    "LONGITUDE": "-114.417797"
  },
  {
    "POSTAL_CODE": "X1A 3M9",
    "LATITUDE": "62.443463",
    "LONGITUDE": "-114.423957"
  },
  {
    "POSTAL_CODE": "X1A 3H7",
    "LATITUDE": "62.442665",
    "LONGITUDE": "-114.42952"
  },
  {
    "POSTAL_CODE": "X1A 1N6",
    "LATITUDE": "62.452686",
    "LONGITUDE": "-114.363812"
  },
  {
    "POSTAL_CODE": "X0E 0N0",
    "LATITUDE": "61.864099",
    "LONGITUDE": "-121.3594"
  },
  {
    "POSTAL_CODE": "X1A 1H2",
    "LATITUDE": "62.451083",
    "LONGITUDE": "-114.363027"
  },
  {
    "POSTAL_CODE": "X1A 3P3",
    "LATITUDE": "62.4434742",
    "LONGITUDE": "-114.429913"
  },
  {
    "POSTAL_CODE": "X1A 1C4",
    "LATITUDE": "62.4547302",
    "LONGITUDE": "-114.3705021"
  },
  {
    "POSTAL_CODE": "X1A 1S3",
    "LATITUDE": "62.454392",
    "LONGITUDE": "-114.374985"
  },
  {
    "POSTAL_CODE": "X0E 0A7",
    "LATITUDE": "61.3576238",
    "LONGITUDE": "-117.6606538"
  },
  {
    "POSTAL_CODE": "X1A 1Y9",
    "LATITUDE": "62.4443001",
    "LONGITUDE": "-114.3993862"
  },
  {
    "POSTAL_CODE": "X1A 2B7",
    "LATITUDE": "62.44646",
    "LONGITUDE": "-114.38974"
  },
  {
    "POSTAL_CODE": "X0E 1G2",
    "LATITUDE": "60.812056",
    "LONGITUDE": "-115.791671"
  },
  {
    "POSTAL_CODE": "X1A 1X1",
    "LATITUDE": "62.4480116",
    "LONGITUDE": "-114.3680556"
  },
  {
    "POSTAL_CODE": "X1A 3W3",
    "LATITUDE": "62.454393",
    "LONGITUDE": "-114.419772"
  },
  {
    "POSTAL_CODE": "X1A 1W7",
    "LATITUDE": "62.45",
    "LONGITUDE": "-114.372594"
  },
  {
    "POSTAL_CODE": "X1A 3V5",
    "LATITUDE": "62.452431",
    "LONGITUDE": "-114.415925"
  },
  {
    "POSTAL_CODE": "X1A 3R1",
    "LATITUDE": "62.4502215",
    "LONGITUDE": "-114.4178228"
  },
  {
    "POSTAL_CODE": "X1A 3J1",
    "LATITUDE": "62.435439",
    "LONGITUDE": "-114.418506"
  },
  {
    "POSTAL_CODE": "X1A 3R6",
    "LATITUDE": "62.4536605",
    "LONGITUDE": "-114.3684896"
  },
  {
    "POSTAL_CODE": "X1A 1V4",
    "LATITUDE": "62.451672",
    "LONGITUDE": "-114.374048"
  },
  {
    "POSTAL_CODE": "X1A 3B7",
    "LATITUDE": "62.439015",
    "LONGITUDE": "-114.417765"
  },
  {
    "POSTAL_CODE": "X1A 2B1",
    "LATITUDE": "62.4455303",
    "LONGITUDE": "-114.3861639"
  },
  {
    "POSTAL_CODE": "X1A 1Y4",
    "LATITUDE": "62.448633",
    "LONGITUDE": "-114.381754"
  },
  {
    "POSTAL_CODE": "X1A 3T5",
    "LATITUDE": "62.458078",
    "LONGITUDE": "-114.376594"
  },
  {
    "POSTAL_CODE": "X1A 2E9",
    "LATITUDE": "62.464596",
    "LONGITUDE": "-114.349655"
  },
  {
    "POSTAL_CODE": "X1A 2L2",
    "LATITUDE": "62.443728",
    "LONGITUDE": "-114.384948"
  },
  {
    "POSTAL_CODE": "X1A 1Y2",
    "LATITUDE": "62.447863",
    "LONGITUDE": "-114.372884"
  },
  {
    "POSTAL_CODE": "X1A 3M8",
    "LATITUDE": "62.442952",
    "LONGITUDE": "-114.424855"
  },
  {
    "POSTAL_CODE": "X1A 3C1",
    "LATITUDE": "62.448253",
    "LONGITUDE": "-114.36914"
  },
  {
    "POSTAL_CODE": "X1A 3S8",
    "LATITUDE": "62.453633",
    "LONGITUDE": "-114.372961"
  },
  {
    "POSTAL_CODE": "X1A 3G7",
    "LATITUDE": "62.443386",
    "LONGITUDE": "-114.427535"
  },
  {
    "POSTAL_CODE": "X1A 2T8",
    "LATITUDE": "62.472515",
    "LONGITUDE": "-114.344261"
  },
  {
    "POSTAL_CODE": "X1A 3L5",
    "LATITUDE": "62.445887",
    "LONGITUDE": "-114.419031"
  },
  {
    "POSTAL_CODE": "X1A 1J5",
    "LATITUDE": "62.462607",
    "LONGITUDE": "-114.356068"
  },
  {
    "POSTAL_CODE": "X1A 2P3",
    "LATITUDE": "62.451124",
    "LONGITUDE": "-114.376882"
  },
  {
    "POSTAL_CODE": "X0E 0B1",
    "LATITUDE": "61.8665504455566",
    "LONGITUDE": "-121.361526489258"
  },
  {
    "POSTAL_CODE": "X1A 2A3",
    "LATITUDE": "62.4618",
    "LONGITUDE": "-114.353032"
  },
  {
    "POSTAL_CODE": "X1A 2M6",
    "LATITUDE": "62.451875",
    "LONGITUDE": "-114.370629"
  },
  {
    "POSTAL_CODE": "X0E 0Y0",
    "LATITUDE": "62.825373",
    "LONGITUDE": "-116.063757"
  },
  {
    "POSTAL_CODE": "X1A 3X4",
    "LATITUDE": "62.45917",
    "LONGITUDE": "-114.365234"
  },
  {
    "POSTAL_CODE": "X1A 1L9",
    "LATITUDE": "62.455619",
    "LONGITUDE": "-114.367981"
  },
  {
    "POSTAL_CODE": "X1A 1S6",
    "LATITUDE": "62.4528962",
    "LONGITUDE": "-114.3717062"
  },
  {
    "POSTAL_CODE": "X0E 0R4",
    "LATITUDE": "60.647486",
    "LONGITUDE": "-115.982194"
  },
  {
    "POSTAL_CODE": "X1A 2H8",
    "LATITUDE": "62.444032",
    "LONGITUDE": "-114.40213"
  },
  {
    "POSTAL_CODE": "X1A 0G2",
    "LATITUDE": "62.462645",
    "LONGITUDE": "-114.373789"
  },
  {
    "POSTAL_CODE": "X1A 1R7",
    "LATITUDE": "62.454464",
    "LONGITUDE": "-114.373056"
  },
  {
    "POSTAL_CODE": "X1A 0A4",
    "LATITUDE": "62.4494655",
    "LONGITUDE": "-114.3715245"
  },
  {
    "POSTAL_CODE": "X1A 3R7",
    "LATITUDE": "62.4539283",
    "LONGITUDE": "-114.3690672"
  },
  {
    "POSTAL_CODE": "X1A 3Z6",
    "LATITUDE": "62.453181",
    "LONGITUDE": "-114.42105"
  },
  {
    "POSTAL_CODE": "X1A 1G5",
    "LATITUDE": "62.447654",
    "LONGITUDE": "-114.376699"
  },
  {
    "POSTAL_CODE": "X1A 3L8",
    "LATITUDE": "62.445671",
    "LONGITUDE": "-114.426892"
  },
  {
    "POSTAL_CODE": "X1A 1V5",
    "LATITUDE": "62.451803",
    "LONGITUDE": "-114.373765"
  },
  {
    "POSTAL_CODE": "X1A 1L1",
    "LATITUDE": "62.456229",
    "LONGITUDE": "-114.366903"
  },
  {
    "POSTAL_CODE": "X0G 0A0",
    "LATITUDE": "60.235895",
    "LONGITUDE": "-123.462936"
  },
  {
    "POSTAL_CODE": "X1A 2H5",
    "LATITUDE": "62.467797",
    "LONGITUDE": "-114.346197"
  },
  {
    "POSTAL_CODE": "X1A 2Y7",
    "LATITUDE": "62.440096",
    "LONGITUDE": "-114.406739"
  },
  {
    "POSTAL_CODE": "X0E 0B9",
    "LATITUDE": "63.830248",
    "LONGITUDE": "-117.388092"
  },
  {
    "POSTAL_CODE": "X0E 0T0",
    "LATITUDE": "68.37389",
    "LONGITUDE": "-133.747108"
  },
  {
    "POSTAL_CODE": "X1A 2R5",
    "LATITUDE": "62.450757",
    "LONGITUDE": "-114.383788"
  },
  {
    "POSTAL_CODE": "X1A 0C5",
    "LATITUDE": "62.450827",
    "LONGITUDE": "-114.383734"
  },
  {
    "POSTAL_CODE": "X1A 3X8",
    "LATITUDE": "62.458481",
    "LONGITUDE": "-114.457177"
  },
  {
    "POSTAL_CODE": "X1A 1P8",
    "LATITUDE": "62.45261",
    "LONGITUDE": "-114.366512"
  },
  {
    "POSTAL_CODE": "X1A 3M1",
    "LATITUDE": "62.444791",
    "LONGITUDE": "-114.424537"
  },
  {
    "POSTAL_CODE": "X1A 2J5",
    "LATITUDE": "62.463844",
    "LONGITUDE": "-114.352137"
  },
  {
    "POSTAL_CODE": "X1A 3C6",
    "LATITUDE": "62.445644",
    "LONGITUDE": "-114.37125"
  },
  {
    "POSTAL_CODE": "X1A 1W8",
    "LATITUDE": "62.448487",
    "LONGITUDE": "-114.369132"
  },
  {
    "POSTAL_CODE": "X1A 2M1",
    "LATITUDE": "62.451871",
    "LONGITUDE": "-114.370629"
  },
  {
    "POSTAL_CODE": "X0E 0Z0",
    "LATITUDE": "68.372277",
    "LONGITUDE": "-133.737145"
  },
  {
    "POSTAL_CODE": "X1A 2X2",
    "LATITUDE": "62.444956",
    "LONGITUDE": "-114.399872"
  },
  {
    "POSTAL_CODE": "X1A 2A4",
    "LATITUDE": "62.450315",
    "LONGITUDE": "-114.387575"
  },
  {
    "POSTAL_CODE": "X1A 0G8",
    "LATITUDE": "62.462645",
    "LONGITUDE": "-114.373789"
  },
  {
    "POSTAL_CODE": "X1A 1W6",
    "LATITUDE": "62.450204",
    "LONGITUDE": "-114.373053"
  },
  {
    "POSTAL_CODE": "X1A 2V4",
    "LATITUDE": "62.442497",
    "LONGITUDE": "-114.368467"
  },
  {
    "POSTAL_CODE": "X0E 0A1",
    "LATITUDE": "69.4473266601563",
    "LONGITUDE": "-133.03515625"
  },
  {
    "POSTAL_CODE": "X1A 0E6",
    "LATITUDE": "62.454471",
    "LONGITUDE": "-114.375124"
  },
  {
    "POSTAL_CODE": "X1A 2B4",
    "LATITUDE": "62.443971",
    "LONGITUDE": "-114.379772"
  },
  {
    "POSTAL_CODE": "X1A 2E5",
    "LATITUDE": "62.4687937",
    "LONGITUDE": "-114.3465371"
  },
  {
    "POSTAL_CODE": "X1A 3H2",
    "LATITUDE": "62.455081",
    "LONGITUDE": "-114.360092"
  },
  {
    "POSTAL_CODE": "X1A 1Z9",
    "LATITUDE": "62.461336",
    "LONGITUDE": "-114.353214"
  },
  {
    "POSTAL_CODE": "X1A 2L1",
    "LATITUDE": "62.4444011",
    "LONGITUDE": "-114.3850993"
  },
  {
    "POSTAL_CODE": "X1A 3E3",
    "LATITUDE": "62.436529",
    "LONGITUDE": "-114.417025"
  },
  {
    "POSTAL_CODE": "X1A 3M3",
    "LATITUDE": "62.444104",
    "LONGITUDE": "-114.425837"
  },
  {
    "POSTAL_CODE": "X1A 0C9",
    "LATITUDE": "62.450827",
    "LONGITUDE": "-114.383734"
  },
  {
    "POSTAL_CODE": "X1A 3T6",
    "LATITUDE": "62.450309",
    "LONGITUDE": "-114.423195"
  },
  {
    "POSTAL_CODE": "X1A 3A3",
    "LATITUDE": "62.4530305",
    "LONGITUDE": "-114.3742367"
  },
  {
    "POSTAL_CODE": "X1A 2E6",
    "LATITUDE": "62.46867",
    "LONGITUDE": "-114.346482"
  },
  {
    "POSTAL_CODE": "X1A 3V1",
    "LATITUDE": "62.451003",
    "LONGITUDE": "-114.408072"
  },
  {
    "POSTAL_CODE": "X1A 3Y4",
    "LATITUDE": "62.4530887",
    "LONGITUDE": "-114.3627571"
  },
  {
    "POSTAL_CODE": "X1A 2R2",
    "LATITUDE": "62.453808",
    "LONGITUDE": "-114.370052"
  },
  {
    "POSTAL_CODE": "X1A 0A5",
    "LATITUDE": "62.4494655",
    "LONGITUDE": "-114.3715245"
  },
  {
    "POSTAL_CODE": "X1A 3G8",
    "LATITUDE": "62.443736",
    "LONGITUDE": "-114.428494"
  },
  {
    "POSTAL_CODE": "X1A 3N8",
    "LATITUDE": "62.4401318",
    "LONGITUDE": "-114.4239974"
  },
  {
    "POSTAL_CODE": "X1A 1X6",
    "LATITUDE": "62.446923",
    "LONGITUDE": "-114.370497"
  },
  {
    "POSTAL_CODE": "X1A 1X4",
    "LATITUDE": "62.447822",
    "LONGITUDE": "-114.370029"
  },
  {
    "POSTAL_CODE": "X1A 1P3",
    "LATITUDE": "62.455139",
    "LONGITUDE": "-114.371777"
  },
  {
    "POSTAL_CODE": "X1A 2Y6",
    "LATITUDE": "62.4401655",
    "LONGITUDE": "-114.406396"
  },
  {
    "POSTAL_CODE": "X1A 3Y8",
    "LATITUDE": "62.43469",
    "LONGITUDE": "-114.413937"
  },
  {
    "POSTAL_CODE": "X1A 2V2",
    "LATITUDE": "62.446215",
    "LONGITUDE": "-114.37384"
  },
  {
    "POSTAL_CODE": "X1A 2E8",
    "LATITUDE": "62.466805",
    "LONGITUDE": "-114.347455"
  },
  {
    "POSTAL_CODE": "X1A 3A8",
    "LATITUDE": "62.4418577",
    "LONGITUDE": "-114.41445"
  },
  {
    "POSTAL_CODE": "X1A 2C4",
    "LATITUDE": "62.450235",
    "LONGITUDE": "-114.383657"
  },
  {
    "POSTAL_CODE": "X1A 2W8",
    "LATITUDE": "62.4447339",
    "LONGITUDE": "-114.374611"
  },
  {
    "POSTAL_CODE": "X1A 3V4",
    "LATITUDE": "62.453663",
    "LONGITUDE": "-114.423084"
  },
  {
    "POSTAL_CODE": "X1A 1E4",
    "LATITUDE": "62.451671",
    "LONGITUDE": "-114.376718"
  },
  {
    "POSTAL_CODE": "X1A 2A8",
    "LATITUDE": "62.4458157",
    "LONGITUDE": "-114.3882942"
  },
  {
    "POSTAL_CODE": "X1A 2X1",
    "LATITUDE": "62.443518",
    "LONGITUDE": "-114.387208"
  },
  {
    "POSTAL_CODE": "X1A 2T2",
    "LATITUDE": "62.463362",
    "LONGITUDE": "-114.35209"
  },
  {
    "POSTAL_CODE": "X1A 2K5",
    "LATITUDE": "62.450424",
    "LONGITUDE": "-114.356815"
  },
  {
    "POSTAL_CODE": "X1A 2C9",
    "LATITUDE": "62.450236",
    "LONGITUDE": "-114.383657"
  },
  {
    "POSTAL_CODE": "X1A 2T6",
    "LATITUDE": "62.458698",
    "LONGITUDE": "-114.355653"
  },
  {
    "POSTAL_CODE": "X1A 3L6",
    "LATITUDE": "62.445524",
    "LONGITUDE": "-114.421246"
  },
  {
    "POSTAL_CODE": "X1A 3K7",
    "LATITUDE": "62.4438997",
    "LONGITUDE": "-114.4194032"
  },
  {
    "POSTAL_CODE": "X1A 3E1",
    "LATITUDE": "62.436302",
    "LONGITUDE": "-114.419012"
  },
  {
    "POSTAL_CODE": "X1A 1W2",
    "LATITUDE": "62.449722",
    "LONGITUDE": "-114.369513"
  },
  {
    "POSTAL_CODE": "X1A 2R9",
    "LATITUDE": "62.4543149",
    "LONGITUDE": "-114.3564357"
  },
  {
    "POSTAL_CODE": "X1A 2L5",
    "LATITUDE": "62.467194",
    "LONGITUDE": "-114.347472"
  },
  {
    "POSTAL_CODE": "X1A 3W5",
    "LATITUDE": "62.454643",
    "LONGITUDE": "-114.414661"
  },
  {
    "POSTAL_CODE": "X1A 2K3",
    "LATITUDE": "62.452664",
    "LONGITUDE": "-114.356195"
  },
  {
    "POSTAL_CODE": "X1A 0C2",
    "LATITUDE": "62.450827",
    "LONGITUDE": "-114.383734"
  },
  {
    "POSTAL_CODE": "X1A 2H4",
    "LATITUDE": "62.453415",
    "LONGITUDE": "-114.383015"
  },
  {
    "POSTAL_CODE": "X1A 1H1",
    "LATITUDE": "62.451765",
    "LONGITUDE": "-114.365519"
  },
  {
    "POSTAL_CODE": "X1A 3P7",
    "LATITUDE": "62.443565",
    "LONGITUDE": "-114.419437"
  },
  {
    "POSTAL_CODE": "X1A 1B2",
    "LATITUDE": "62.453208",
    "LONGITUDE": "-114.377068"
  },
  {
    "POSTAL_CODE": "X1A 1V6",
    "LATITUDE": "62.4510419",
    "LONGITUDE": "-114.3724035"
  },
  {
    "POSTAL_CODE": "X0E 0B8",
    "LATITUDE": "63.830248",
    "LONGITUDE": "-117.388092"
  },
  {
    "POSTAL_CODE": "X0E 0B4",
    "LATITUDE": "63.830248",
    "LONGITUDE": "-117.388092"
  },
  {
    "POSTAL_CODE": "X0E 0K0",
    "LATITUDE": "64.915502",
    "LONGITUDE": "-125.461448"
  },
  {
    "POSTAL_CODE": "X1A 1T4",
    "LATITUDE": "62.452246",
    "LONGITUDE": "-114.372835"
  },
  {
    "POSTAL_CODE": "X1A 2J8",
    "LATITUDE": "62.45985",
    "LONGITUDE": "-114.355659"
  },
  {
    "POSTAL_CODE": "X1A 1H3",
    "LATITUDE": "62.450376",
    "LONGITUDE": "-114.364928"
  },
  {
    "POSTAL_CODE": "X1A 1E9",
    "LATITUDE": "62.449092",
    "LONGITUDE": "-114.380958"
  },
  {
    "POSTAL_CODE": "X1A 0B8",
    "LATITUDE": "62.4494655",
    "LONGITUDE": "-114.3715245"
  },
  {
    "POSTAL_CODE": "X1A 1J7",
    "LATITUDE": "62.457842",
    "LONGITUDE": "-114.363459"
  },
  {
    "POSTAL_CODE": "X1A 1W9",
    "LATITUDE": "62.449145",
    "LONGITUDE": "-114.370605"
  },
  {
    "POSTAL_CODE": "X1A 2N6",
    "LATITUDE": "62.451556",
    "LONGITUDE": "-114.3747"
  },
  {
    "POSTAL_CODE": "X1A 2K4",
    "LATITUDE": "62.452034",
    "LONGITUDE": "-114.356348"
  },
  {
    "POSTAL_CODE": "X0E 0R7",
    "LATITUDE": "60.8187828",
    "LONGITUDE": "-115.7747688"
  },
  {
    "POSTAL_CODE": "X1A 3W7",
    "LATITUDE": "62.449432",
    "LONGITUDE": "-114.412954"
  },
  {
    "POSTAL_CODE": "X1A 0A9",
    "LATITUDE": "62.4494655",
    "LONGITUDE": "-114.3715245"
  },
  {
    "POSTAL_CODE": "X1A 3Y5",
    "LATITUDE": "62.441855",
    "LONGITUDE": "-114.403059"
  },
  {
    "POSTAL_CODE": "X1A 2S8",
    "LATITUDE": "62.450238",
    "LONGITUDE": "-114.383657"
  },
  {
    "POSTAL_CODE": "X1A 2Y4",
    "LATITUDE": "62.440885",
    "LONGITUDE": "-114.405117"
  },
  {
    "POSTAL_CODE": "X1A 3K1",
    "LATITUDE": "62.448754",
    "LONGITUDE": "-114.364889"
  },
  {
    "POSTAL_CODE": "X1A 3J4",
    "LATITUDE": "62.440482",
    "LONGITUDE": "-114.41075"
  },
  {
    "POSTAL_CODE": "X1A 2A1",
    "LATITUDE": "62.460934",
    "LONGITUDE": "-114.353477"
  },
  {
    "POSTAL_CODE": "X0E 0S0",
    "LATITUDE": "70.735854",
    "LONGITUDE": "-117.779364"
  },
  {
    "POSTAL_CODE": "X0E 0A9",
    "LATITUDE": "60.816218",
    "LONGITUDE": "-115.7853653"
  },
  {
    "POSTAL_CODE": "X1A 3M4",
    "LATITUDE": "62.443313",
    "LONGITUDE": "-114.42645"
  },
  {
    "POSTAL_CODE": "X1A 1R1",
    "LATITUDE": "62.451494",
    "LONGITUDE": "-114.363528"
  },
  {
    "POSTAL_CODE": "X1A 0B9",
    "LATITUDE": "62.4494655",
    "LONGITUDE": "-114.3715245"
  },
  {
    "POSTAL_CODE": "X1A 1V2",
    "LATITUDE": "62.452942",
    "LONGITUDE": "-114.3765"
  },
  {
    "POSTAL_CODE": "X0E 0V0",
    "LATITUDE": "65.305301",
    "LONGITUDE": "-126.705712"
  },
  {
    "POSTAL_CODE": "X1A 1E3",
    "LATITUDE": "62.452277",
    "LONGITUDE": "-114.375481"
  },
  {
    "POSTAL_CODE": "X1A 2X7",
    "LATITUDE": "62.443358",
    "LONGITUDE": "-114.407293"
  },
  {
    "POSTAL_CODE": "X1A 2Z1",
    "LATITUDE": "62.439798",
    "LONGITUDE": "-114.4050304"
  },
  {
    "POSTAL_CODE": "X0E 1G1",
    "LATITUDE": "60.81016",
    "LONGITUDE": "-115.79337"
  },
  {
    "POSTAL_CODE": "X1A 3H4",
    "LATITUDE": "62.441696",
    "LONGITUDE": "-114.426485"
  },
  {
    "POSTAL_CODE": "X1A 2S9",
    "LATITUDE": "62.46433",
    "LONGITUDE": "-114.34965"
  },
  {
    "POSTAL_CODE": "X1A 2R1",
    "LATITUDE": "62.451941",
    "LONGITUDE": "-114.368314"
  },
  {
    "POSTAL_CODE": "X1A 2J9",
    "LATITUDE": "62.459834",
    "LONGITUDE": "-114.355659"
  },
  {
    "POSTAL_CODE": "X0E 1R0",
    "LATITUDE": "64.117855",
    "LONGITUDE": "-117.312207"
  },
  {
    "POSTAL_CODE": "X1A 3S7",
    "LATITUDE": "62.4558585",
    "LONGITUDE": "-114.3734792"
  },
  {
    "POSTAL_CODE": "X1A 1K5",
    "LATITUDE": "62.457781",
    "LONGITUDE": "-114.367892"
  },
  {
    "POSTAL_CODE": "X0E 0A6",
    "LATITUDE": "65.1888507",
    "LONGITUDE": "-123.4227518"
  },
  {
    "POSTAL_CODE": "X1A 1T6",
    "LATITUDE": "62.4510115",
    "LONGITUDE": "-114.3699145"
  },
  {
    "POSTAL_CODE": "X1A 1X9",
    "LATITUDE": "62.448352",
    "LONGITUDE": "-114.373978"
  },
  {
    "POSTAL_CODE": "X1A 1J9",
    "LATITUDE": "62.457369",
    "LONGITUDE": "-114.364533"
  },
  {
    "POSTAL_CODE": "X1A 1S2",
    "LATITUDE": "62.4527016",
    "LONGITUDE": "-114.3688163"
  },
  {
    "POSTAL_CODE": "X1A 3T3",
    "LATITUDE": "62.462307",
    "LONGITUDE": "-114.413374"
  },
  {
    "POSTAL_CODE": "X1A 1N5",
    "LATITUDE": "62.452629",
    "LONGITUDE": "-114.363679"
  },
  {
    "POSTAL_CODE": "X1A 2C6",
    "LATITUDE": "62.449679",
    "LONGITUDE": "-114.387382"
  },
  {
    "POSTAL_CODE": "X1A 2X4",
    "LATITUDE": "62.44543",
    "LONGITUDE": "-114.400973"
  },
  {
    "POSTAL_CODE": "X0E 0G0",
    "LATITUDE": "65.185509",
    "LONGITUDE": "-123.419779"
  },
  {
    "POSTAL_CODE": "X1A 2V1",
    "LATITUDE": "62.447059",
    "LONGITUDE": "-114.373239"
  },
  {
    "POSTAL_CODE": "X1A 1R2",
    "LATITUDE": "62.44947",
    "LONGITUDE": "-114.360239"
  },
  {
    "POSTAL_CODE": "X1A 3S3",
    "LATITUDE": "62.4561463",
    "LONGITUDE": "-114.371597"
  },
  {
    "POSTAL_CODE": "X1A 3Z2",
    "LATITUDE": "62.4443218",
    "LONGITUDE": "-114.3753132"
  },
  {
    "POSTAL_CODE": "X1A 3K2",
    "LATITUDE": "62.442036",
    "LONGITUDE": "-114.355322"
  },
  {
    "POSTAL_CODE": "X1A 1S7",
    "LATITUDE": "62.4513425",
    "LONGITUDE": "-114.3681965"
  },
  {
    "POSTAL_CODE": "X1A 3N2",
    "LATITUDE": "62.440712",
    "LONGITUDE": "-114.425888"
  },
  {
    "POSTAL_CODE": "X1A 0C3",
    "LATITUDE": "62.450827",
    "LONGITUDE": "-114.383734"
  },
  {
    "POSTAL_CODE": "X1A 3K9",
    "LATITUDE": "62.445006",
    "LONGITUDE": "-114.419302"
  },
  {
    "POSTAL_CODE": "X0E 0R3",
    "LATITUDE": "60.8030974",
    "LONGITUDE": "-115.7916894"
  },
  {
    "POSTAL_CODE": "X1A 1N3",
    "LATITUDE": "62.454473",
    "LONGITUDE": "-114.368161"
  },
  {
    "POSTAL_CODE": "X1A 1V8",
    "LATITUDE": "62.449775",
    "LONGITUDE": "-114.369628"
  },
  {
    "POSTAL_CODE": "X1A 2V7",
    "LATITUDE": "62.445274",
    "LONGITUDE": "-114.369108"
  },
  {
    "POSTAL_CODE": "X1A 3E7",
    "LATITUDE": "62.4395895",
    "LONGITUDE": "-114.422648"
  },
  {
    "POSTAL_CODE": "X0E 0C1",
    "LATITUDE": "61.0334654",
    "LONGITUDE": "-123.3833648"
  },
  {
    "POSTAL_CODE": "X1A 3W8",
    "LATITUDE": "62.462564",
    "LONGITUDE": "-114.363354"
  },
  {
    "POSTAL_CODE": "X1A 2K6",
    "LATITUDE": "62.450303",
    "LONGITUDE": "-114.357002"
  },
  {
    "POSTAL_CODE": "X1A 0E5",
    "LATITUDE": "62.4529394",
    "LONGITUDE": "-114.4176008"
  },
  {
    "POSTAL_CODE": "X1A 1T7",
    "LATITUDE": "62.451601",
    "LONGITUDE": "-114.371162"
  },
  {
    "POSTAL_CODE": "X1A 3P1",
    "LATITUDE": "62.442373",
    "LONGITUDE": "-114.412896"
  },
  {
    "POSTAL_CODE": "X1A 3V2",
    "LATITUDE": "62.4515055",
    "LONGITUDE": "-114.408866"
  },
  {
    "POSTAL_CODE": "X1A 1M2",
    "LATITUDE": "62.4533936",
    "LONGITUDE": "-114.3629788"
  },
  {
    "POSTAL_CODE": "X1A 3B2",
    "LATITUDE": "62.440907",
    "LONGITUDE": "-114.41639"
  },
  {
    "POSTAL_CODE": "X1A 1B4",
    "LATITUDE": "62.458706",
    "LONGITUDE": "-114.362247"
  },
  {
    "POSTAL_CODE": "X1A 2N5",
    "LATITUDE": "62.451123",
    "LONGITUDE": "-114.376882"
  },
  {
    "POSTAL_CODE": "X1A 2C1",
    "LATITUDE": "62.451638",
    "LONGITUDE": "-114.384216"
  },
  {
    "POSTAL_CODE": "X1A 0B1",
    "LATITUDE": "62.4494655",
    "LONGITUDE": "-114.3715245"
  },
  {
    "POSTAL_CODE": "X0E 0L0",
    "LATITUDE": "61.351716",
    "LONGITUDE": "-117.644001"
  },
  {
    "POSTAL_CODE": "X1A 3X7",
    "LATITUDE": "62.45564",
    "LONGITUDE": "-114.366749"
  },
  {
    "POSTAL_CODE": "X1A 1Z4",
    "LATITUDE": "62.462768",
    "LONGITUDE": "-114.351829"
  },
  {
    "POSTAL_CODE": "X1A 2C8",
    "LATITUDE": "62.449556",
    "LONGITUDE": "-114.387221"
  },
  {
    "POSTAL_CODE": "X1A 3K8",
    "LATITUDE": "62.443586",
    "LONGITUDE": "-114.414704"
  },
  {
    "POSTAL_CODE": "X1A 2B6",
    "LATITUDE": "62.44646",
    "LONGITUDE": "-114.38974"
  },
  {
    "POSTAL_CODE": "X1A 0E4",
    "LATITUDE": "62.4515535",
    "LONGITUDE": "-114.3712533"
  },
  {
    "POSTAL_CODE": "X1A 3X1",
    "LATITUDE": "62.440599",
    "LONGITUDE": "-114.416786"
  },
  {
    "POSTAL_CODE": "X1A 2H1",
    "LATITUDE": "62.4656695",
    "LONGITUDE": "-114.3481205"
  },
  {
    "POSTAL_CODE": "X1A 3V7",
    "LATITUDE": "62.453355",
    "LONGITUDE": "-114.41424"
  },
  {
    "POSTAL_CODE": "X1A 3P2",
    "LATITUDE": "62.440199",
    "LONGITUDE": "-114.411586"
  },
  {
    "POSTAL_CODE": "X1A 0H1",
    "LATITUDE": "62.4451051",
    "LONGITUDE": "-114.403553"
  },
  {
    "POSTAL_CODE": "X0E 0R0",
    "LATITUDE": "60.810755",
    "LONGITUDE": "-115.792592"
  },
  {
    "POSTAL_CODE": "X1A 2M3",
    "LATITUDE": "62.451873",
    "LONGITUDE": "-114.370629"
  },
  {
    "POSTAL_CODE": "X1A 3W1",
    "LATITUDE": "62.453058",
    "LONGITUDE": "-114.4269"
  },
  {
    "POSTAL_CODE": "X1A 3X9",
    "LATITUDE": "62.453681",
    "LONGITUDE": "-114.35406"
  },
  {
    "POSTAL_CODE": "X1A 0B7",
    "LATITUDE": "62.4494655",
    "LONGITUDE": "-114.3715245"
  },
  {
    "POSTAL_CODE": "X1A 3W2",
    "LATITUDE": "62.456333",
    "LONGITUDE": "-114.415698"
  },
  {
    "POSTAL_CODE": "X1A 1A3",
    "LATITUDE": "62.460042",
    "LONGITUDE": "-114.359472"
  },
  {
    "POSTAL_CODE": "X1A 2W7",
    "LATITUDE": "62.444884",
    "LONGITUDE": "-114.374613"
  },
  {
    "POSTAL_CODE": "X0E 0A3",
    "LATITUDE": "67.436445",
    "LONGITUDE": "-134.880755"
  },
  {
    "POSTAL_CODE": "X1A 1B9",
    "LATITUDE": "62.456114",
    "LONGITUDE": "-114.367189"
  },
  {
    "POSTAL_CODE": "X1A 1P9",
    "LATITUDE": "62.451804",
    "LONGITUDE": "-114.364421"
  },
  {
    "POSTAL_CODE": "X1A 0H2",
    "LATITUDE": "62.4539717",
    "LONGITUDE": "-114.3717887"
  },
  {
    "POSTAL_CODE": "X1A 2W5",
    "LATITUDE": "62.444484",
    "LONGITUDE": "-114.372787"
  },
  {
    "POSTAL_CODE": "X1A 3S4",
    "LATITUDE": "62.4553488",
    "LONGITUDE": "-114.3697883"
  },
  {
    "POSTAL_CODE": "X1A 1G2",
    "LATITUDE": "62.4501895",
    "LONGITUDE": "-114.376442"
  },
  {
    "POSTAL_CODE": "X1A 1S1",
    "LATITUDE": "62.452765",
    "LONGITUDE": "-114.368961"
  },
  {
    "POSTAL_CODE": "X1A 2X9",
    "LATITUDE": "62.444059",
    "LONGITUDE": "-114.404964"
  },
  {
    "POSTAL_CODE": "X1A 3W4",
    "LATITUDE": "62.456466",
    "LONGITUDE": "-114.416949"
  },
  {
    "POSTAL_CODE": "X1A 1M3",
    "LATITUDE": "62.45435",
    "LONGITUDE": "-114.365147"
  },
  {
    "POSTAL_CODE": "X1A 3J9",
    "LATITUDE": "62.443452",
    "LONGITUDE": "-114.420013"
  },
  {
    "POSTAL_CODE": "X1A 3R8",
    "LATITUDE": "62.453931",
    "LONGITUDE": "-114.369353"
  },
  {
    "POSTAL_CODE": "X1A 3H1",
    "LATITUDE": "62.441875",
    "LONGITUDE": "-114.428955"
  },
  {
    "POSTAL_CODE": "X1A 3P9",
    "LATITUDE": "62.449494",
    "LONGITUDE": "-114.41542"
  },
  {
    "POSTAL_CODE": "X0E 0A4",
    "LATITUDE": "60.00552",
    "LONGITUDE": "-111.8849379"
  },
  {
    "POSTAL_CODE": "X1A 2W6",
    "LATITUDE": "62.444669",
    "LONGITUDE": "-114.37445"
  },
  {
    "POSTAL_CODE": "X0E 0R2",
    "LATITUDE": "60.795118",
    "LONGITUDE": "-115.803409"
  },
  {
    "POSTAL_CODE": "X1A 3G3",
    "LATITUDE": "62.458495",
    "LONGITUDE": "-114.411417"
  },
  {
    "POSTAL_CODE": "X1A 2Y5",
    "LATITUDE": "62.44274",
    "LONGITUDE": "-114.406265"
  },
  {
    "POSTAL_CODE": "X1A 3X2",
    "LATITUDE": "62.441843",
    "LONGITUDE": "-114.398208"
  },
  {
    "POSTAL_CODE": "X0E 0A2",
    "LATITUDE": "66.2556759",
    "LONGITUDE": "-128.634021"
  },
  {
    "POSTAL_CODE": "X1A 3J2",
    "LATITUDE": "62.466473",
    "LONGITUDE": "-114.348583"
  },
  {
    "POSTAL_CODE": "X1A 1H5",
    "LATITUDE": "62.450216",
    "LONGITUDE": "-114.359122"
  },
  {
    "POSTAL_CODE": "X1A 1J8",
    "LATITUDE": "62.457678",
    "LONGITUDE": "-114.365492"
  },
  {
    "POSTAL_CODE": "X1A 3H3",
    "LATITUDE": "62.441235",
    "LONGITUDE": "-114.426849"
  },
  {
    "POSTAL_CODE": "X0E 0B2",
    "LATITUDE": "67.4418167",
    "LONGITUDE": "-133.7429147"
  },
  {
    "POSTAL_CODE": "X1A 2S6",
    "LATITUDE": "62.44646",
    "LONGITUDE": "-114.38974"
  },
  {
    "POSTAL_CODE": "X1A 2L6",
    "LATITUDE": "62.466252",
    "LONGITUDE": "-114.349834"
  },
  {
    "POSTAL_CODE": "X1A 2P5",
    "LATITUDE": "62.45453",
    "LONGITUDE": "-114.370606"
  },
  {
    "POSTAL_CODE": "X1A 0G7",
    "LATITUDE": "62.462645",
    "LONGITUDE": "-114.373789"
  },
  {
    "POSTAL_CODE": "X1A 3K6",
    "LATITUDE": "62.443268",
    "LONGITUDE": "-114.418166"
  },
  {
    "POSTAL_CODE": "X1A 2Y9",
    "LATITUDE": "62.440364",
    "LONGITUDE": "-114.406306"
  },
  {
    "POSTAL_CODE": "X1A 1N4",
    "LATITUDE": "62.45404",
    "LONGITUDE": "-114.366947"
  },
  {
    "POSTAL_CODE": "X1A 1L4",
    "LATITUDE": "62.455341",
    "LONGITUDE": "-114.364905"
  },
  {
    "POSTAL_CODE": "X1A 3R9",
    "LATITUDE": "62.445482",
    "LONGITUDE": "-114.411136"
  },
  {
    "POSTAL_CODE": "X1A 2N7",
    "LATITUDE": "62.453791",
    "LONGITUDE": "-114.374775"
  },
  {
    "POSTAL_CODE": "X1A 1X5",
    "LATITUDE": "62.448609",
    "LONGITUDE": "-114.371755"
  },
  {
    "POSTAL_CODE": "X1A 1H7",
    "LATITUDE": "62.449573",
    "LONGITUDE": "-114.361461"
  },
  {
    "POSTAL_CODE": "X1A 1T8",
    "LATITUDE": "62.450227",
    "LONGITUDE": "-114.36824"
  },
  {
    "POSTAL_CODE": "X1A 1Y1",
    "LATITUDE": "62.448206",
    "LONGITUDE": "-114.373354"
  },
  {
    "POSTAL_CODE": "X1A 2K2",
    "LATITUDE": "62.4543507",
    "LONGITUDE": "-114.3564293"
  },
  {
    "POSTAL_CODE": "X0E 1C0",
    "LATITUDE": "69.443224",
    "LONGITUDE": "-133.03722"
  },
  {
    "POSTAL_CODE": "X1A 0B3",
    "LATITUDE": "62.4494655",
    "LONGITUDE": "-114.3715245"
  },
  {
    "POSTAL_CODE": "X1A 2G4",
    "LATITUDE": "62.445114",
    "LONGITUDE": "-114.389507"
  },
  {
    "POSTAL_CODE": "X1A 3N6",
    "LATITUDE": "62.439134",
    "LONGITUDE": "-114.42467"
  },
  {
    "POSTAL_CODE": "X1A 3A6",
    "LATITUDE": "62.438831",
    "LONGITUDE": "-114.419729"
  },
  {
    "POSTAL_CODE": "X1A 3B9",
    "LATITUDE": "62.420245",
    "LONGITUDE": "-114.415012"
  },
  {
    "POSTAL_CODE": "X1A 2J1",
    "LATITUDE": "62.444886",
    "LONGITUDE": "-114.400049"
  },
  {
    "POSTAL_CODE": "X1A 0E2",
    "LATITUDE": "62.449145",
    "LONGITUDE": "-114.370605"
  },
  {
    "POSTAL_CODE": "X1A 3Z3",
    "LATITUDE": "62.445352",
    "LONGITUDE": "-114.411249"
  },
  {
    "POSTAL_CODE": "X1A 3M5",
    "LATITUDE": "62.443288",
    "LONGITUDE": "-114.425853"
  },
  {
    "POSTAL_CODE": "X1A 1T5",
    "LATITUDE": "62.452376",
    "LONGITUDE": "-114.372551"
  },
  {
    "POSTAL_CODE": "X1A 3C2",
    "LATITUDE": "62.420246",
    "LONGITUDE": "-114.415012"
  },
  {
    "POSTAL_CODE": "X1A 2B9",
    "LATITUDE": "62.450233",
    "LONGITUDE": "-114.383657"
  },
  {
    "POSTAL_CODE": "X1A 3B6",
    "LATITUDE": "62.440293",
    "LONGITUDE": "-114.4171798"
  },
  {
    "POSTAL_CODE": "X1A 0B5",
    "LATITUDE": "62.4494655",
    "LONGITUDE": "-114.3715245"
  },
  {
    "POSTAL_CODE": "X0E 0B5",
    "LATITUDE": "63.830248",
    "LONGITUDE": "-117.388092"
  },
  {
    "POSTAL_CODE": "X1A 3N1",
    "LATITUDE": "62.445054",
    "LONGITUDE": "-114.424477"
  },
  {
    "POSTAL_CODE": "X1A 3B1",
    "LATITUDE": "62.438734",
    "LONGITUDE": "-114.413175"
  },
  {
    "POSTAL_CODE": "X1A 3P4",
    "LATITUDE": "62.441709",
    "LONGITUDE": "-114.428464"
  },
  {
    "POSTAL_CODE": "X1A 2J7",
    "LATITUDE": "62.460654",
    "LONGITUDE": "-114.355678"
  },
  {
    "POSTAL_CODE": "X1A 2A7",
    "LATITUDE": "62.446243",
    "LONGITUDE": "-114.388843"
  },
  {
    "POSTAL_CODE": "X1A 0B4",
    "LATITUDE": "62.4494655",
    "LONGITUDE": "-114.3715245"
  },
  {
    "POSTAL_CODE": "X1A 1Z3",
    "LATITUDE": "62.468444",
    "LONGITUDE": "-114.347642"
  },
  {
    "POSTAL_CODE": "X0E 0A5",
    "LATITUDE": "68.3607437",
    "LONGITUDE": "-133.7230177"
  },
  {
    "POSTAL_CODE": "X1A 2X5",
    "LATITUDE": "62.445269",
    "LONGITUDE": "-114.4006775"
  },
  {
    "POSTAL_CODE": "X1A 1T9",
    "LATITUDE": "62.449383",
    "LONGITUDE": "-114.366323"
  },
  {
    "POSTAL_CODE": "X1A 2M9",
    "LATITUDE": "62.451878",
    "LONGITUDE": "-114.370629"
  },
  {
    "POSTAL_CODE": "X1A 0E7",
    "LATITUDE": "62.434508",
    "LONGITUDE": "-114.427324"
  },
  {
    "POSTAL_CODE": "X1A 1R3",
    "LATITUDE": "62.4496167",
    "LONGITUDE": "-114.3610069"
  },
  {
    "POSTAL_CODE": "X1A 0H4",
    "LATITUDE": "62.4544853",
    "LONGITUDE": "-114.4072369"
  },
  {
    "POSTAL_CODE": "X0E 1E0",
    "LATITUDE": "63.230575",
    "LONGITUDE": "-123.468663"
  },
  {
    "POSTAL_CODE": "X0E 0R6",
    "LATITUDE": "60.809292",
    "LONGITUDE": "-115.804884"
  },
  {
    "POSTAL_CODE": "X1A 1S8",
    "LATITUDE": "62.452096",
    "LONGITUDE": "-114.369932"
  },
  {
    "POSTAL_CODE": "X1A 2B2",
    "LATITUDE": "62.445819",
    "LONGITUDE": "-114.384158"
  },
  {
    "POSTAL_CODE": "X0E 0A8",
    "LATITUDE": "61.172054",
    "LONGITUDE": "-113.673764"
  },
  {
    "POSTAL_CODE": "X1A 0B2",
    "LATITUDE": "62.4494655",
    "LONGITUDE": "-114.3715245"
  },
  {
    "POSTAL_CODE": "X1A 0A8",
    "LATITUDE": "62.4494655",
    "LONGITUDE": "-114.3715245"
  },
  {
    "POSTAL_CODE": "X1A 2X8",
    "LATITUDE": "62.44407",
    "LONGITUDE": "-114.404989"
  },
  {
    "POSTAL_CODE": "X1A 3E9",
    "LATITUDE": "62.4414275",
    "LONGITUDE": "-114.42296"
  },
  {
    "POSTAL_CODE": "X1A 3X5",
    "LATITUDE": "62.463367",
    "LONGITUDE": "-114.365989"
  },
  {
    "POSTAL_CODE": "X1A 1V9",
    "LATITUDE": "62.449352",
    "LONGITUDE": "-114.36844"
  },
  {
    "POSTAL_CODE": "X0E 1W0",
    "LATITUDE": "64.095045",
    "LONGITUDE": "-114.205649"
  },
  {
    "POSTAL_CODE": "X1A 2M5",
    "LATITUDE": "62.455639",
    "LONGITUDE": "-114.366749"
  },
  {
    "POSTAL_CODE": "X1A 3L3",
    "LATITUDE": "62.445486",
    "LONGITUDE": "-114.421154"
  },
  {
    "POSTAL_CODE": "X1A 1X2",
    "LATITUDE": "62.448841",
    "LONGITUDE": "-114.37227"
  },
  {
    "POSTAL_CODE": "X1A 3B3",
    "LATITUDE": "62.446115",
    "LONGITUDE": "-114.374254"
  },
  {
    "POSTAL_CODE": "X1A 0G6",
    "LATITUDE": "62.434",
    "LONGITUDE": "-114.421147"
  },
  {
    "POSTAL_CODE": "X1A 1B5",
    "LATITUDE": "62.457688",
    "LONGITUDE": "-114.363187"
  },
  {
    "POSTAL_CODE": "X1A 2N4",
    "LATITUDE": "62.451555",
    "LONGITUDE": "-114.3747"
  },
  {
    "POSTAL_CODE": "X1A 2R3",
    "LATITUDE": "62.446685",
    "LONGITUDE": "-114.390164"
  },
  {
    "POSTAL_CODE": "X0E 0R5",
    "LATITUDE": "60.821411",
    "LONGITUDE": "-115.784803"
  },
  {
    "POSTAL_CODE": "X1A 1W1",
    "LATITUDE": "62.449031",
    "LONGITUDE": "-114.368003"
  },
  {
    "POSTAL_CODE": "X1A 2P7",
    "LATITUDE": "62.451125",
    "LONGITUDE": "-114.376882"
  },
  {
    "POSTAL_CODE": "X1A 2K8",
    "LATITUDE": "62.444187",
    "LONGITUDE": "-114.385051"
  },
  {
    "POSTAL_CODE": "X1A 1A4",
    "LATITUDE": "62.458472",
    "LONGITUDE": "-114.364339"
  },
  {
    "POSTAL_CODE": "X1A 1W3",
    "LATITUDE": "62.450541",
    "LONGITUDE": "-114.373771"
  },
  {
    "POSTAL_CODE": "X1A 1L2",
    "LATITUDE": "62.456743",
    "LONGITUDE": "-114.368434"
  },
  {
    "POSTAL_CODE": "X1A 1K7",
    "LATITUDE": "62.453103",
    "LONGITUDE": "-114.356973"
  },
  {
    "POSTAL_CODE": "X0E 0B7",
    "LATITUDE": "63.830248",
    "LONGITUDE": "-117.388092"
  },
  {
    "POSTAL_CODE": "X1A 2C7",
    "LATITUDE": "62.4494963",
    "LONGITUDE": "-114.3871438"
  },
  {
    "POSTAL_CODE": "X1A 2C3",
    "LATITUDE": "62.450234",
    "LONGITUDE": "-114.383657"
  },
  {
    "POSTAL_CODE": "X1A 3S9",
    "LATITUDE": "62.452719",
    "LONGITUDE": "-114.374247"
  },
  {
    "POSTAL_CODE": "X1A 3W6",
    "LATITUDE": "62.448903",
    "LONGITUDE": "-114.410099"
  },
  {
    "POSTAL_CODE": "X1A 3E8",
    "LATITUDE": "62.440084",
    "LONGITUDE": "-114.423886"
  },
  {
    "POSTAL_CODE": "X1A 1X7",
    "LATITUDE": "62.451743",
    "LONGITUDE": "-114.381419"
  },
  {
    "POSTAL_CODE": "X1A 3Y9",
    "LATITUDE": "62.453487",
    "LONGITUDE": "-114.413994"
  },
  {
    "POSTAL_CODE": "X1A 2N3",
    "LATITUDE": "62.450812",
    "LONGITUDE": "-114.370695"
  },
  {
    "POSTAL_CODE": "X1A 1B3",
    "LATITUDE": "62.459217",
    "LONGITUDE": "-114.361106"
  },
  {
    "POSTAL_CODE": "X1A 2G9",
    "LATITUDE": "62.462569",
    "LONGITUDE": "-114.354747"
  },
  {
    "POSTAL_CODE": "X1A 3H5",
    "LATITUDE": "62.440895",
    "LONGITUDE": "-114.425576"
  },
  {
    "POSTAL_CODE": "X1A 0G4",
    "LATITUDE": "62.428363",
    "LONGITUDE": "-114.413392"
  },
  {
    "POSTAL_CODE": "X1A 3N3",
    "LATITUDE": "62.439186",
    "LONGITUDE": "-114.428731"
  },
  {
    "POSTAL_CODE": "X1A 3P6",
    "LATITUDE": "62.443268",
    "LONGITUDE": "-114.418166"
  },
  {
    "POSTAL_CODE": "X1A 2V8",
    "LATITUDE": "62.446109",
    "LONGITUDE": "-114.373547"
  },
  {
    "POSTAL_CODE": "X1A 1G6",
    "LATITUDE": "62.447028",
    "LONGITUDE": "-114.377832"
  },
  {
    "POSTAL_CODE": "X1A 2N9",
    "LATITUDE": "62.450258",
    "LONGITUDE": "-114.371935"
  },
  {
    "POSTAL_CODE": "X1A 0C7",
    "LATITUDE": "62.450827",
    "LONGITUDE": "-114.383734"
  },
  {
    "POSTAL_CODE": "X1A 2L8",
    "LATITUDE": "62.451122",
    "LONGITUDE": "-114.376882"
  },
  {
    "POSTAL_CODE": "X1A 1Y7",
    "LATITUDE": "62.451627",
    "LONGITUDE": "-114.385069"
  },
  {
    "POSTAL_CODE": "X1A 0A6",
    "LATITUDE": "62.4494655",
    "LONGITUDE": "-114.3715245"
  },
  {
    "POSTAL_CODE": "X1A 3N9",
    "LATITUDE": "62.440134",
    "LONGITUDE": "-114.40656"
  },
  {
    "POSTAL_CODE": "X1A 3P8",
    "LATITUDE": "62.450737",
    "LONGITUDE": "-114.412677"
  },
  {
    "POSTAL_CODE": "X1A 3S5",
    "LATITUDE": "62.454743",
    "LONGITUDE": "-114.370767"
  },
  {
    "POSTAL_CODE": "X1A 1Y8",
    "LATITUDE": "62.44419",
    "LONGITUDE": "-114.399976"
  },
  {
    "POSTAL_CODE": "X1A 3C8",
    "LATITUDE": "62.461415",
    "LONGITUDE": "-114.352642"
  },
  {
    "POSTAL_CODE": "X1A 3G6",
    "LATITUDE": "62.442314",
    "LONGITUDE": "-114.423659"
  },
  {
    "POSTAL_CODE": "X1A 1Z5",
    "LATITUDE": "62.462842",
    "LONGITUDE": "-114.351855"
  },
  {
    "POSTAL_CODE": "X1A 1H9",
    "LATITUDE": "62.454357",
    "LONGITUDE": "-114.357261"
  },
  {
    "POSTAL_CODE": "X1A 3G1",
    "LATITUDE": "62.442691",
    "LONGITUDE": "-114.424854"
  },
  {
    "POSTAL_CODE": "X1A 2W9",
    "LATITUDE": "62.443475",
    "LONGITUDE": "-114.386822"
  },
  {
    "POSTAL_CODE": "X1A 1Z1",
    "LATITUDE": "62.469928",
    "LONGITUDE": "-114.346829"
  },
  {
    "POSTAL_CODE": "X1A 1E7",
    "LATITUDE": "62.4492384",
    "LONGITUDE": "-114.3805949"
  },
  {
    "POSTAL_CODE": "X0E 0M0",
    "LATITUDE": "61.170126",
    "LONGITUDE": "-113.66459"
  },
  {
    "POSTAL_CODE": "X1A 2W4",
    "LATITUDE": "62.444938",
    "LONGITUDE": "-114.373502"
  },
  {
    "POSTAL_CODE": "X1A 3E2",
    "LATITUDE": "62.436175",
    "LONGITUDE": "-114.418826"
  },
  {
    "POSTAL_CODE": "X1A 2Z2",
    "LATITUDE": "62.4392597",
    "LONGITUDE": "-114.4065114"
  },
  {
    "POSTAL_CODE": "X0E 0J0",
    "LATITUDE": "67.432219",
    "LONGITUDE": "-134.866502"
  },
  {
    "POSTAL_CODE": "X1A 3S6",
    "LATITUDE": "62.44998",
    "LONGITUDE": "-114.421841"
  },
  {
    "POSTAL_CODE": "X1A 3R3",
    "LATITUDE": "62.450892",
    "LONGITUDE": "-114.412979"
  },
  {
    "POSTAL_CODE": "X1A 0C4",
    "LATITUDE": "62.4494655",
    "LONGITUDE": "-114.3715245"
  },
  {
    "POSTAL_CODE": "X1A 0H3",
    "LATITUDE": "62.4539717",
    "LONGITUDE": "-114.3717887"
  },
  {
    "POSTAL_CODE": "X1A 1M4",
    "LATITUDE": "62.451152",
    "LONGITUDE": "-114.356245"
  },
  {
    "POSTAL_CODE": "X1A 2P9",
    "LATITUDE": "62.451559",
    "LONGITUDE": "-114.3747"
  },
  {
    "POSTAL_CODE": "X1A 2N1",
    "LATITUDE": "62.450256",
    "LONGITUDE": "-114.371935"
  },
  {
    "POSTAL_CODE": "X0E 0R8",
    "LATITUDE": "60.8143937",
    "LONGITUDE": "-115.7778869"
  },
  {
    "POSTAL_CODE": "X1A 3Y6",
    "LATITUDE": "62.445686",
    "LONGITUDE": "-114.388"
  },
  {
    "POSTAL_CODE": "X1A 3G5",
    "LATITUDE": "62.4511662",
    "LONGITUDE": "-114.3625201"
  },
  {
    "POSTAL_CODE": "X1A 3J7",
    "LATITUDE": "62.438923",
    "LONGITUDE": "-114.420787"
  },
  {
    "POSTAL_CODE": "X1A 3J5",
    "LATITUDE": "62.441762",
    "LONGITUDE": "-114.428622"
  },
  {
    "POSTAL_CODE": "X1A 2E1",
    "LATITUDE": "62.461865",
    "LONGITUDE": "-114.3572"
  },
  {
    "POSTAL_CODE": "X1A 3V8",
    "LATITUDE": "62.454131",
    "LONGITUDE": "-114.421284"
  },
  {
    "POSTAL_CODE": "X1A 0A7",
    "LATITUDE": "62.4494655",
    "LONGITUDE": "-114.3715245"
  },
  {
    "POSTAL_CODE": "X1A 2N2",
    "LATITUDE": "62.450257",
    "LONGITUDE": "-114.371935"
  },
  {
    "POSTAL_CODE": "X1A 3R2",
    "LATITUDE": "62.45229",
    "LONGITUDE": "-114.420647"
  },
  {
    "POSTAL_CODE": "X1A 1G3",
    "LATITUDE": "62.45117",
    "LONGITUDE": "-114.375315"
  },
  {
    "POSTAL_CODE": "X1A 1H8",
    "LATITUDE": "62.454349",
    "LONGITUDE": "-114.356429"
  },
  {
    "POSTAL_CODE": "X1A 3B5",
    "LATITUDE": "62.444405",
    "LONGITUDE": "-114.409915"
  },
  {
    "POSTAL_CODE": "X1A 2K9",
    "LATITUDE": "62.4454364",
    "LONGITUDE": "-114.3855485"
  },
  {
    "POSTAL_CODE": "X0E 0B3",
    "LATITUDE": "64.9034227",
    "LONGITUDE": "-125.5733163"
  },
  {
    "POSTAL_CODE": "X1A 1L7",
    "LATITUDE": "62.456832",
    "LONGITUDE": "-114.370562"
  },
  {
    "POSTAL_CODE": "X1A 2Y8",
    "LATITUDE": "62.442637",
    "LONGITUDE": "-114.407737"
  },
  {
    "POSTAL_CODE": "X1A 3H9",
    "LATITUDE": "62.435604",
    "LONGITUDE": "-114.418646"
  },
  {
    "POSTAL_CODE": "X1A 1V1",
    "LATITUDE": "62.449232",
    "LONGITUDE": "-114.365976"
  },
  {
    "POSTAL_CODE": "X1A 1G4",
    "LATITUDE": "62.448571",
    "LONGITUDE": "-114.374776"
  },
  {
    "POSTAL_CODE": "X1A 2T5",
    "LATITUDE": "62.46003",
    "LONGITUDE": "-114.35397"
  },
  {
    "POSTAL_CODE": "X1A 3E5",
    "LATITUDE": "62.437911",
    "LONGITUDE": "-114.419014"
  },
  {
    "POSTAL_CODE": "X1A 2R4",
    "LATITUDE": "62.448876",
    "LONGITUDE": "-114.386336"
  },
  {
    "POSTAL_CODE": "X1A 3G2",
    "LATITUDE": "62.459191",
    "LONGITUDE": "-114.355343"
  }
]